Metadata-Version: 2.1
Name: itchat-uos
Version: 1.4.1
Summary: 复活Itchat, 仅仅需要 pip install itchat-uos, good luck !
Home-page: https://github.com/why2lyj/ItChat-UOS
Author: Snow Wang
Author-email: admin@farseer.vip
License: MIT
Keywords: wechat itchat api robot weixin personal extend
Platform: UNKNOWN
Classifier: Development Status :: 3 - Alpha
Classifier: Intended Audience :: Developers
Classifier: Topic :: Software Development :: Libraries :: Python Modules
Classifier: License :: OSI Approved :: MIT License
Classifier: Programming Language :: Python :: 2
Classifier: Programming Language :: Python :: 2.6
Classifier: Programming Language :: Python :: 2.7
Classifier: Programming Language :: Python :: 3.5
Classifier: Programming Language :: Python :: 3.6
Classifier: Programming Language :: Python :: 3.7
Classifier: Programming Language :: Python :: 3.8
Classifier: Programming Language :: Python :: 3.9
License-File: LICENSE
